breathe/__init__.py
breathe/client.py
breathe/exceptions.py
breathe/models/__init__.py
breathe/models/courses.py
breathe/models/employees.py
python_breathe-0.0.2.dist-info/LICENSE
python_breathe-0.0.2.dist-info/METADATA
python_breathe-0.0.2.dist-info/WHEEL
python_breathe-0.0.2.dist-info/top_level.txt
python_breathe-0.0.2.dist-info/RECORD
