Metadata-Version: 2.1
Name: python-breathe
Version: 0.0.2
Summary: A Python wrapper for the Breathe HR API
Home-page: https://github.com/kieranhogg/breathe
Author: Kieran Hogg
Author-email: kieran.hogg@gmail.com
License: UNKNOWN
Platform: UNKNOWN
Classifier: Programming Language :: Python :: 3
Classifier: License :: OSI Approved :: MIT License
Classifier: Operating System :: OS Independent
